discord_raw_mcp/__init__.py
discord_raw_mcp/server.py
mseep_discord_raw_mcp-0.1.4.dist-info/licenses/LICENSE
mseep_discord_raw_mcp-0.1.4.dist-info/METADATA
mseep_discord_raw_mcp-0.1.4.dist-info/WHEEL
mseep_discord_raw_mcp-0.1.4.dist-info/entry_points.txt
mseep_discord_raw_mcp-0.1.4.dist-info/top_level.txt
mseep_discord_raw_mcp-0.1.4.dist-info/RECORD
