Metadata-Version: 2.4
Name: mseep-discord-raw-mcp
Version: 0.1.4
Summary: Discord Raw API MCP Server
Author-email: mseep <support@skydeck.ai>
Requires-Python: >=3.10
License-File: LICENSE
Requires-Dist: discord.py>=2.3.2
Requires-Dist: mcp>=1.2.0
Requires-Dist: aiohttp>=3.9.1
Dynamic: license-file
